rna2seg/__init__.py
rna2seg/_constant.py
rna2seg/ci_unet.py
rna2seg/logger.py
rna2seg/models.py
rna2seg/train.py
rna2seg/utils.py
rna2seg/dataset_zarr/RNA2segDataset.py
rna2seg/dataset_zarr/__init__.py
rna2seg/dataset_zarr/background.py
rna2seg/dataset_zarr/consistency.py
rna2seg/dataset_zarr/data_augmentation.py
rna2seg/dataset_zarr/patches.py
rna2seg/dataset_zarr/staining_transcript.py
rna2seg-0.1.5.dist-info/LICENSE
rna2seg-0.1.5.dist-info/METADATA
rna2seg-0.1.5.dist-info/WHEEL
rna2seg-0.1.5.dist-info/top_level.txt
rna2seg-0.1.5.dist-info/RECORD
