Metadata-Version: 2.1
Name: rna2seg
Version: 0.1.5
Summary: A generalist model for cell segmentation in image-based spatial transcriptomics
Author-email: Thomas Defard <thomas.defard@minesparis.psl.eu>, Alice Blondel <alice.blondel@minesparis.psl.eu>
License: MIT
Classifier: Programming Language :: Python :: 3
Classifier: Operating System :: OS Independent
Requires-Python: >=3.10
License-File: LICENSE
Requires-Dist: instanseg-torch ==0.0.8
Requires-Dist: sopa ==2.0.4
Requires-Dist: cellpose ==3.0.8
Requires-Dist: einops ==0.8.0
Requires-Dist: xarray ==2024.10.0
Requires-Dist: huggingface-hub
Requires-Dist: torchvision ==0.21
Requires-Dist: tensorboard ==2.16
Requires-Dist: albumentations ==1.4
Requires-Dist: rasterio ==1.4
